<?xml version="1.0" encoding="UTF-8"?>
<beans xmlns="http://www.springframework.org/schema/beans"
	xmlns:xsi="http://www.w3.org/2001/XMLSchema-instance" xmlns:aop="http://www.springframework.org/schema/aop"
	xsi:schemaLocation="http://www.springframework.org/schema/beans http://www.springframework.org/schema/beans/spring-beans-3.1.xsd  http://www.springframework.org/schema/aop  http://www.springframework.org/schema/aop/spring-aop-3.1.xsd">
	<bean id="common" class="com.test.spring.aop.Common" />
	<bean id="check" class="com.test.spring.aop.Check" />
	<!-- 使用XML标签配置AOP,还能用Annotation方式  -->
	<aop:config>
		<aop:aspect id="myAop" ref="check">
			<aop:pointcut id="target"
				expression="execution(* com.test.spring.aop.Common.execute(..))" />
			<aop:before method="checkValidity" pointcut-ref="target" />
			<aop:after method="addLog" pointcut-ref="target" />
		</aop:aspect>
	</aop:config>
</beans>